jsonl.py
py_jsonl-1.3.21.dist-info/licenses/LICENSE
py_jsonl-1.3.21.dist-info/METADATA
py_jsonl-1.3.21.dist-info/WHEEL
py_jsonl-1.3.21.dist-info/top_level.txt
py_jsonl-1.3.21.dist-info/RECORD
