Metadata-Version: 2.4
Name: py-jsonl
Version: 1.3.21
Summary: A lightweight Python library for handling jsonlines files.
Author-email: rmoralespp <rmoralespp@gmail.com>
Project-URL: Source, https://github.com/rmoralespp/jsonl
Project-URL: Homepage, https://github.com/rmoralespp/jsonl
Project-URL: Changelog, https://github.com/rmoralespp/jsonl/blob/main/CHANGELOG.md
Project-URL: Issues, https://github.com/rmoralespp/jsonl/issues
Project-URL: Documentation, https://rmoralespp.github.io/jsonl/
Keywords: jsonlines,ndjson,jsonl,json,gzip,bzip2,xz,zip,tar,utilities,serialization,deserialization
Classifier: Programming Language :: Python
Classifier: Programming Language :: Python :: 3 :: Only
Classifier: Programming Language :: Python :: 3.8
Classifier: Programming Language :: Python :: 3.9
Classifier: Programming Language :: Python :: 3.10
Classifier: Programming Language :: Python :: 3.11
Classifier: Programming Language :: Python :: 3.12
Classifier: Programming Language :: Python :: 3.13
Classifier: Programming Language :: Python :: 3.14
Classifier: Intended Audience :: Developers
Classifier: Intended Audience :: Information Technology
Classifier: Topic :: Software Development :: Libraries :: Python Modules
Classifier: Topic :: Internet
Classifier: Topic :: Utilities
Classifier: Topic :: File Formats :: JSON
Requires-Python: >=3.8
License-File: LICENSE
Dynamic: license-file
